{
  "slug": "guide-triple-tips",
  "cat": "חבילה משולבת",
  "date": "2026-06-20",
  "read": 4,
  "title": "חבילה משולבת — 5 טיפים לחסוך יותר בחבילת כל-כלול | חוסך",
  "desc": "אתם כבר על חבילה משולבת אינטרנט+TV+סלולר? כך תחסכו עוד: ניהול שירותים, מה לוותר עליו ומה לשדרג, ומתי לא משתלם חבילה אחת.",
  "h1": "חבילה משולבת — 5 טיפים לחיסכון אמיתי",
  "tldr": "חבילה משולבת (Triple Play) לא תמיד הכי זולה — לפעמים ספקים נפרדים זולים יותר ב-₪50–₪100 לחודש. כן, בדקו: מה 'כלול' לפי הסכם? מה המחיר לאחר ההטבה? האם אתם משתמשים בכל המרכיבים? מחשבון חוסך יכול לחשב את זה בשבילכם.",
  "sections": [
    {
      "h2": "טיפ 1: בדקו מה המחיר האמיתי",
      "ul": [
        "מחיר שנה ראשונה vs. מחיר קבוע: 'חבילה ב-₪150/חודש' יכולה להיות ₪220 אחרי 12–24 חודש.",
        "פרקו כל מרכיב: אינטרנט X + TV Y + סלולר Z = X+Y+Z. האם הסכום נמוך ממה שמשלמים?",
        "ראו את החשבון: אחת לשנה בדקו את 'מה כולל' הסכם הנוכחי — לא מה הבטיחו בעל פה.",
        "חשבון דורש ניתוח: HOT/yes כוללים בחשבון שורות שונות לכל שירות — חברו אותן."
      ]
    },
    {
      "h2": "טיפ 2: וותרו על מה שלא משתמשים בו",
      "ul": [
        "טלוויזיה: האם אתם צופים? Netflix+Disney+ בנפרד לעיתים זולים מחבילת TV הכלולה.",
        "קווי ביתי: 70% מהישראלים לא משתמשים בקוו ביתי — כבו וחסכו ₪20–₪40.",
        "VOD: HOT Vod / yes VOD — האם אתם משתמשים? אם לא, בקשו להוריד מהחבילה.",
        "גיבוי ענן/אנטי-וירוס: לרוב ניתן לוותר ולהשתמש בשירות אחר (Google Drive, iCloud)."
      ]
    },
    {
      "h2": "טיפ 3: השוו כל שנה — מחירים יורדים",
      "ul": [
        "שוק התקשורת הישראלי תחרותי: כל שנה נכנסים מבצעים חדשים. מה שהיה המחיר הטוב לפני 2 שנים — אולי יקר היום.",
        "בדקו ב-חוסך: הכניסו את הרכיבים שלכם — אינטרנט מהירות/TV/סלולר GB — ורואים את ההשוואה.",
        "פנו למחלקת שימור: 'קיבלתי הצעה מ-X' → לרוב מציעים להתאים מחיר.",
        "מחלקת שימור HOT: 1202. פרטנר: *1901. yes: 1235."
      ]
    },
    {
      "h2": "טיפ 4: שקלו ספקים נפרדים",
      "ul": [
        "אינטרנט: בזק גלאל (₪80–₹150) + ספק MVNO לסלולר (₪30–₪50) = ₪110–₪200.",
        "לעומת: HOT Triple Play = ₪200–₹350/חודש לכל השירותים.",
        "לא תמיד נפרד זול יותר: HOT/yes מציעים הנחות חבילות שלרוב שווה לבדוק.",
        "כשנפרד יותר זול: כשאחד המרכיבים לא בשימוש (כמו TV שלא צופים)."
      ]
    },
    {
      "h2": "טיפ 5: נהלו משא ומתן בסוף חוזה",
      "ul": [
        "הזמן הטוב ביותר: כשהחוזה מסתיים — לא קנסות יציאה, הספק מתאמץ לשמור.",
        "הכינו הצעה מתחרה: הדפיסו/צלמו הצעה מחוסך או מספק מתחרה.",
        "בקשו: הורדת מחיר, שדרוג חינמי (יותר גיגה/ערוצים), ביטול שורה שלא משתמשים.",
        "הסכם חדש: לרוב תקבלו 12–24 חודש מחיר חדש. בדקו מחיר אחרי ההטבה גם הפעם."
      ]
    }
  ],
  "faq": [
    ["חבילה משולבת — יתרון אמיתי או שיווק?", "שניהם. ההנחה על החבילה לרוב אמיתית (₪50–₹100 לחודש לעומת ספקים נפרדים) — אבל רק אם משתמשים בכל המרכיבים. אם לא צופים ב-TV — החבילה עשויה להיות יקרה יותר ממה שנדמה."],
    ["כמה אפשר לחסוך במשא ומתן על חבילה?", "בממוצע ₪50–₪150 לחודש. ידוע מקרים של ₪200+ חיסכון חודשי. ההצלחה תלויה: בכמה זמן לקוח ותיק, בהצעה מתחרה אמינה, ובמיומנות ההסדרה. ראו מדריך שימור."],
    ["HOT vs. yes — מה ההבדל בחבילה משולבת?", "HOT: כבל (בסביבות 80% מהיישובים). yes: לוויין/IPTV (כל הארץ). HOT זמין בעיקר בערים גדולות; yes נגיש גם בפריפריה. ערוצי TV דומים מאוד — ההבדל העיקרי הוא אינפרסטרוקטורה ואיכות שירות לקוחות."],
    ["אינטרנט מהיר + Netflix — זול יותר מחבילת TV?", "לרוב כן! אינטרנט גלאל ₪100 + Netflix ₪50 + Disney+ ₪40 = ₪190, ללא ספורט חי. חבילת HOT עם TV = ₪180–₪250+. אם לא צריכים ספורט חי — Netflix+גלאל יוצא זול ואיכותי יותר לרוב."]
  ]
}
